{
	"credit": "Yuushya",
	"ambientocclusion": false,
	"texture_size": [32, 32],
	"textures": {
		"0": "yuushya:block/oak_log",
		"particle": "yuushya:block/oak_leaves_branch_medium",
		"2_0": "yuushya:block/oak_leaves_branch_medium"
	},
	"elements": [
		{
			"from": [7, 0, 7],
			"to": [9, 16, 9],
			"faces": {
				"north": {"uv": [1, 0, 3, 16], "texture": "#0"},
				"east": {"uv": [1, 0, 3, 16], "texture": "#0"},
				"south": {"uv": [1, 0, 3, 16], "texture": "#0"},
				"west": {"uv": [2, 0, 4, 16], "texture": "#0"},
				"up": {"uv": [2, 2, 4, 4], "texture": "#0"},
				"down": {"uv": [1.5, 1.5, 3.5, 3.5], "texture": "#0"}
			}
		},
		{
			"from": [-4, 9, -2],
			"to": [16, 9, 19],
			"rotation": {"angle": 22.5, "axis": "z", "origin": [13, 19, 9]},
			"faces": {
				"north": {"uv": [0, 0, 0, 10], "rotation": 270, "texture": "#2_0"},
				"east": {"uv": [0, 0, 10.5, 0], "texture": "#2_0"},
				"south": {"uv": [0, 0, 0, 10], "rotation": 90, "texture": "#2_0"},
				"west": {"uv": [0, 0, 10.5, 0], "rotation": 180, "texture": "#2_0"},
				"up": {"uv": [2, 5, 12.5, 15], "rotation": 90, "texture": "#2_0"},
				"down": {"uv": [2, 5, 12.5, 15], "rotation": 90, "texture": "#2_0"}
			}
		},
		{
			"from": [1, 4, -2],
			"to": [22, 19, -2],
			"rotation": {"angle": -22.5, "axis": "x", "origin": [12, 35, -5]},
			"faces": {
				"north": {"uv": [13, 7.5, 2.5, 15], "rotation": 180, "texture": "#2_0"},
				"east": {"uv": [0, 0, 0, 7.5], "texture": "#missing"},
				"south": {"uv": [13, 7.5, 2.5, 15], "rotation": 180, "texture": "#2_0"},
				"west": {"uv": [0, 0, 0, 7.5], "texture": "#missing"},
				"up": {"uv": [0, 0, 10.5, 0], "rotation": 180, "texture": "#missing"},
				"down": {"uv": [0, 0, 10.5, 0], "rotation": 180, "texture": "#missing"}
			}
		},
		{
			"from": [15, 4, 0],
			"to": [20, 4, 4],
			"rotation": {"angle": 22.5, "axis": "y", "origin": [24, 7, 12]},
			"faces": {
				"north": {"uv": [0, 0, 0, 2.5], "rotation": 270, "texture": "#2_0"},
				"east": {"uv": [0, 0, 2, 0], "rotation": 180, "texture": "#2_0"},
				"south": {"uv": [0, 0, 0, 2.5], "rotation": 90, "texture": "#2_0"},
				"west": {"uv": [0, 0, 2, 0], "texture": "#2_0"},
				"up": {"uv": [12, 1.5, 10, 4], "rotation": 90, "texture": "#2_0"},
				"down": {"uv": [12, 1.5, 10, 4], "rotation": 270, "texture": "#2_0"}
			}
		}
	],
	"display": {
		"thirdperson_righthand": {
			"rotation": [75, 45, 0],
			"translation": [0, 2.5, 0],
			"scale": [0.375, 0.375, 0.375]
		},
		"thirdperson_lefthand": {
			"rotation": [75, 45, 0],
			"translation": [0, 2.5, 0],
			"scale": [0.375, 0.375, 0.375]
		},
		"firstperson_righthand": {
			"rotation": [0, 45, 0],
			"translation": [1, 0, 0],
			"scale": [0.3, 0.3, 0.3]
		},
		"firstperson_lefthand": {
			"rotation": [0, 45, 0],
			"translation": [1, 0, 0],
			"scale": [0.3, 0.3, 0.3]
		},
		"ground": {
			"translation": [0, 3, 0],
			"scale": [0.25, 0.25, 0.25]
		},
		"gui": {
			"rotation": [30, 60, 0],
			"translation": [0, -2, 0],
			"scale": [0.6, 0.6, 0.6]
		},
		"fixed": {
			"rotation": [-90, 0, 0],
			"translation": [0, 0, -46],
			"scale": [2, 2, 2]
		}
	},
	"groups": [
		0,
		{
			"name": "leaves_maple",
			"origin": [8, 8, 8],
			"color": 0,
			"children": [1]
		},
		{
			"name": "leaves_maple_medium",
			"origin": [8, 8, 8],
			"color": 0,
			"children": [2]
		},
		{
			"name": "leaves_maple_small",
			"origin": [8, 8, 8],
			"color": 0,
			"children": [3]
		}
	]
}